Metadata-Version: 1.1
Name: pdftablr
Version: 0.1.0
Summary: Python3 implementation of Kyle Cronan's pdftable module, with unit tests
Home-page: https://github.com/philgooch/pdftable
Author: Phil Gooch and Kyle Cronan
Author-email: philgooch@users.noreply.github.com
License: GPLv3
Download-URL: https://github.com/philgooch/pdftable/archive/v0.1.0.tar.gz
Keywords: python3,pdf,table-extraction,tables,information-extraction
Platform: UNKNOWN
Classifier: License :: OSI Approved :: GNU General Public License (GPL)
Classifier: Natural Language :: English
Classifier: Operating System :: OS Independent
Classifier: Programming Language :: Python
Classifier: Topic :: Office/Business
Classifier: Topic :: Software Development :: Libraries
Classifier: Topic :: Text Processing
